Hello_world/__init__.py
decoration/__init__.py
my_module/__init__.py
my_module/backtest/__init__.py
my_module/backtest/test.py
my_module/test_module/__init__.py
AAAA_mymodule-0.1.dist-info/LICENSE.txt
AAAA_mymodule-0.1.dist-info/METADATA
AAAA_mymodule-0.1.dist-info/WHEEL
AAAA_mymodule-0.1.dist-info/top_level.txt
AAAA_mymodule-0.1.dist-info/RECORD
