Metadata-Version: 2.1
Name: AAAA_mymodule
Version: 0.1
Summary: A simple reusable Python module
Author: Nixer,lv
Author-email: 582848910@qq.com
Classifier: Programming Language :: Python :: 3
Classifier: License :: OSI Approved :: MIT License
Classifier: Operating System :: OS Independent
Requires-Python: >=3.8
License-File: LICENSE.txt
Requires-Dist: numpy
Requires-Dist: pandas
